mirakl_api_client/__init__.py
mirakl_api_client/client.py
mirakl_api_client/resources.py
mirakl_api_client/utils.py
mirakl_api_client-0.1.6.dist-info/WHEEL
mirakl_api_client-0.1.6.dist-info/METADATA
mirakl_api_client-0.1.6.dist-info/RECORD
